Metadata-Version: 2.1
Name: lyytkmain
Version: 1.8
Summary: yyjdgui for lyy
Author: lyy
Author-email: 
License: MIT
License-File: LICENSE
